django_admin_shell/__init__.py
django_admin_shell/apps.py
django_admin_shell/forms.py
django_admin_shell/settings.py
django_admin_shell/urls.py
django_admin_shell/views.py
django_admin_shell/migrations/__init__.py
django_admin_shell/static/django_admin_shell/css/bootstrap.min.css.map
django_admin_shell/static/django_admin_shell/css/bootstrap3.min.css
django_admin_shell/static/django_admin_shell/css/shell.css
django_admin_shell/static/django_admin_shell/fonts/glyphicons-halflings-regular.eot
django_admin_shell/static/django_admin_shell/fonts/glyphicons-halflings-regular.svg
django_admin_shell/static/django_admin_shell/fonts/glyphicons-halflings-regular.ttf
django_admin_shell/static/django_admin_shell/fonts/glyphicons-halflings-regular.woff
django_admin_shell/static/django_admin_shell/fonts/glyphicons-halflings-regular.woff2
django_admin_shell/static/django_admin_shell/js/jquery.min.js
django_admin_shell/static/django_admin_shell/js/shell.js
django_admin_shell/static/django_admin_shell/js/shell.min.js
django_admin_shell/static/django_admin_shell/js/linedtextarea/jquery-linedtextarea-license.txt
django_admin_shell/static/django_admin_shell/js/linedtextarea/jquery-linedtextarea.css
django_admin_shell/static/django_admin_shell/js/linedtextarea/jquery-linedtextarea.js
django_admin_shell/templates/django_admin_shell/base.html
django_admin_shell/templates/django_admin_shell/shell.html
django_admin_shell/tests/__init__.py
django_admin_shell/tests/models.py
django_admin_shell/tests/settings.py
django_admin_shell/tests/test_importer.py
django_admin_shell/tests/test_runner.py
django_admin_shell/tests/test_view.py
django_admin_shell/tests/urls.py
django_admin_shell-2.0.1.dist-info/LICENSE
django_admin_shell-2.0.1.dist-info/METADATA
django_admin_shell-2.0.1.dist-info/WHEEL
django_admin_shell-2.0.1.dist-info/top_level.txt
django_admin_shell-2.0.1.dist-info/RECORD
