Metadata-Version: 2.1
Name: django-admin-shell
Version: 2.0.1
Home-page: https://github.com/djk2/django-admin-shell
Author: Grzegorz Tężycki
Author-email: grzegorz.tezycki@gmail.com
License: MIT
Keywords: django admin shell console terminal
Classifier: Environment :: Web Environment
Classifier: Framework :: Django
Classifier: License :: OSI Approved :: MIT License
Classifier: Operating System :: OS Independent
Classifier: Programming Language :: Python
Classifier: Programming Language :: Python :: 3
Classifier: Programming Language :: Python :: 3.7
Classifier: Programming Language :: Python :: 3.8
Classifier: Programming Language :: Python :: 3.10
Classifier: Topic :: Utilities
License-File: LICENSE
Requires-Dist: Django (>=2.0)
